HISTORY.rst
LICENSE.txt
MANIFEST.in
README.md
setup.py
jsroutes/__init__.py
jsroutes/subscribers.py
jsroutes/utils.py
pyramid_jsroutes.egg-info/PKG-INFO
pyramid_jsroutes.egg-info/SOURCES.txt
pyramid_jsroutes.egg-info/dependency_links.txt
pyramid_jsroutes.egg-info/not-zip-safe
pyramid_jsroutes.egg-info/requires.txt
pyramid_jsroutes.egg-info/top_level.txt