Metadata-Version: 1.0
Name: pyramid-jsroutes
Version: 0.1.1
Summary: A pyramid routes composer for javascript.
Home-page: https://github.com/marconi/pyramid-jsroutes
Author: Marconi Moreto
Author-email: caketoad@gmail.com
License: Copyright (c) 2012 Marconi Moreto.
